brownian/__init__.py
brownian/_calck.py
brownian/_rdump.py
brownian/_stan.py
brownian/_version.py
brownian/bayes.py
brownian/ex/brownian-red.h5
brownian/hdf5/__init__.py
brownian/stanmodels/gamma.exe
brownian/stanmodels/gamma.linux
brownian/stanmodels/gamma.osx
brownian/stanmodels/gamma2.exe
brownian/stanmodels/gamma2.linux
brownian/stanmodels/gamma2.osx
brownian/tests/__init__.py
brownian/tests/test__init__.py
brownian/tests/test_bayes.py
brownian/tests/test_calck.py
brownian/tests/testhdf5__init__.py
brownian-0.4.dev7.dist-info/DESCRIPTION.rst
brownian-0.4.dev7.dist-info/METADATA
brownian-0.4.dev7.dist-info/RECORD
brownian-0.4.dev7.dist-info/WHEEL
brownian-0.4.dev7.dist-info/entry_points.txt
brownian-0.4.dev7.dist-info/metadata.json
brownian-0.4.dev7.dist-info/top_level.txt
